Metadata-Version: 2.1
Name: grocery-helpers
Version: 0.2
Summary: Selenium-based Python API for online grocery retailers.
Home-page: https://github.com/ryanfobel/grocery-helpers
Author: Ryan Fobel
Author-email: ryan@fobel.net
License: BSD-3
Keywords: selenium grocery groceries food
Platform: UNKNOWN
